[{"__symbolic":"module","version":3,"metadata":{"BaseField":{"__symbolic":"class","members":{"__ctor__":[{"__symbolic":"constructor","parameters":[{"__symbolic":"error","message":"Expression form not supported","line":9,"character":25}]}]}},"SIGN_IN_FORM":[{"__symbolic":"new","expression":{"__symbolic":"reference","name":"BaseField"},"arguments":[{"key":"email","label":"Email","type":"text","validators":[{"__symbolic":"select","expression":{"__symbolic":"reference","module":"@angular/forms","name":"Validators"},"member":"required"},{"__symbolic":"call","expression":{"__symbolic":"select","expression":{"__symbolic":"reference","module":"@angular/forms","name":"Validators"},"member":"minLength"},"arguments":[8]}]}]},{"__symbolic":"new","expression":{"__symbolic":"reference","name":"BaseField"},"arguments":[{"key":"password","label":"Password","type":"password","validators":[{"__symbolic":"select","expression":{"__symbolic":"reference","module":"@angular/forms","name":"Validators"},"member":"required"},{"__symbolic":"call","expression":{"__symbolic":"select","expression":{"__symbolic":"reference","module":"@angular/forms","name":"Validators"},"member":"minLength"},"arguments":[8]}]}]}],"SIGN_UP_FORM":[{"__symbolic":"new","expression":{"__symbolic":"reference","name":"BaseField"},"arguments":[{"key":"email","label":"Email","type":"text","validators":[{"__symbolic":"select","expression":{"__symbolic":"reference","module":"@angular/forms","name":"Validators"},"member":"required"},{"__symbolic":"call","expression":{"__symbolic":"select","expression":{"__symbolic":"reference","module":"@angular/forms","name":"Validators"},"member":"minLength"},"arguments":[8]}]}]},{"__symbolic":"new","expression":{"__symbolic":"reference","name":"BaseField"},"arguments":[{"key":"password","label":"Password","type":"password","validators":[{"__symbolic":"select","expression":{"__symbolic":"reference","module":"@angular/forms","name":"Validators"},"member":"required"},{"__symbolic":"call","expression":{"__symbolic":"select","expression":{"__symbolic":"reference","module":"@angular/forms","name":"Validators"},"member":"minLength"},"arguments":[8]}]}]},{"__symbolic":"new","expression":{"__symbolic":"reference","name":"BaseField"},"arguments":[{"key":"passwordConfirmation","label":"Password Confirmation","type":"password","validators":[{"__symbolic":"select","expression":{"__symbolic":"reference","module":"@angular/forms","name":"Validators"},"member":"required"},{"__symbolic":"call","expression":{"__symbolic":"select","expression":{"__symbolic":"reference","module":"@angular/forms","name":"Validators"},"member":"minLength"},"arguments":[8]}]}]}],"RESET_PASSWORD_FORM":[{"__symbolic":"new","expression":{"__symbolic":"reference","name":"BaseField"},"arguments":[{"key":"email","label":"Email","type":"text","validators":[{"__symbolic":"select","expression":{"__symbolic":"reference","module":"@angular/forms","name":"Validators"},"member":"required"},{"__symbolic":"call","expression":{"__symbolic":"select","expression":{"__symbolic":"reference","module":"@angular/forms","name":"Validators"},"member":"minLength"},"arguments":[8]}]}]}],"UPDATE_PASSWORD_FORM":[{"__symbolic":"new","expression":{"__symbolic":"reference","name":"BaseField"},"arguments":[{"key":"password","label":"Password","type":"password","validators":[{"__symbolic":"select","expression":{"__symbolic":"reference","module":"@angular/forms","name":"Validators"},"member":"required"},{"__symbolic":"call","expression":{"__symbolic":"select","expression":{"__symbolic":"reference","module":"@angular/forms","name":"Validators"},"member":"minLength"},"arguments":[8]}]}]},{"__symbolic":"new","expression":{"__symbolic":"reference","name":"BaseField"},"arguments":[{"key":"passwordConfirmation","label":"Password Confirmation","type":"password","validators":[{"__symbolic":"select","expression":{"__symbolic":"reference","module":"@angular/forms","name":"Validators"},"member":"required"},{"__symbolic":"call","expression":{"__symbolic":"select","expression":{"__symbolic":"reference","module":"@angular/forms","name":"Validators"},"member":"minLength"},"arguments":[8]}]}]},{"__symbolic":"new","expression":{"__symbolic":"reference","name":"BaseField"},"arguments":[{"key":"passwordCurrent","label":"Old Password","type":"password","validators":[{"__symbolic":"select","expression":{"__symbolic":"reference","module":"@angular/forms","name":"Validators"},"member":"required"},{"__symbolic":"call","expression":{"__symbolic":"select","expression":{"__symbolic":"reference","module":"@angular/forms","name":"Validators"},"member":"minLength"},"arguments":[8]}]}]}]}},{"__symbolic":"module","version":1,"metadata":{"BaseField":{"__symbolic":"class","members":{"__ctor__":[{"__symbolic":"constructor","parameters":[{"__symbolic":"error","message":"Expression form not supported","line":9,"character":25}]}]}},"SIGN_IN_FORM":[{"__symbolic":"new","expression":{"__symbolic":"reference","name":"BaseField"},"arguments":[{"key":"email","label":"Email","type":"text","validators":[{"__symbolic":"select","expression":{"__symbolic":"reference","module":"@angular/forms","name":"Validators"},"member":"required"},{"__symbolic":"call","expression":{"__symbolic":"select","expression":{"__symbolic":"reference","module":"@angular/forms","name":"Validators"},"member":"minLength"},"arguments":[8]}]}]},{"__symbolic":"new","expression":{"__symbolic":"reference","name":"BaseField"},"arguments":[{"key":"password","label":"Password","type":"password","validators":[{"__symbolic":"select","expression":{"__symbolic":"reference","module":"@angular/forms","name":"Validators"},"member":"required"},{"__symbolic":"call","expression":{"__symbolic":"select","expression":{"__symbolic":"reference","module":"@angular/forms","name":"Validators"},"member":"minLength"},"arguments":[8]}]}]}],"SIGN_UP_FORM":[{"__symbolic":"new","expression":{"__symbolic":"reference","name":"BaseField"},"arguments":[{"key":"email","label":"Email","type":"text","validators":[{"__symbolic":"select","expression":{"__symbolic":"reference","module":"@angular/forms","name":"Validators"},"member":"required"},{"__symbolic":"call","expression":{"__symbolic":"select","expression":{"__symbolic":"reference","module":"@angular/forms","name":"Validators"},"member":"minLength"},"arguments":[8]}]}]},{"__symbolic":"new","expression":{"__symbolic":"reference","name":"BaseField"},"arguments":[{"key":"password","label":"Password","type":"password","validators":[{"__symbolic":"select","expression":{"__symbolic":"reference","module":"@angular/forms","name":"Validators"},"member":"required"},{"__symbolic":"call","expression":{"__symbolic":"select","expression":{"__symbolic":"reference","module":"@angular/forms","name":"Validators"},"member":"minLength"},"arguments":[8]}]}]},{"__symbolic":"new","expression":{"__symbolic":"reference","name":"BaseField"},"arguments":[{"key":"passwordConfirmation","label":"Password Confirmation","type":"password","validators":[{"__symbolic":"select","expression":{"__symbolic":"reference","module":"@angular/forms","name":"Validators"},"member":"required"},{"__symbolic":"call","expression":{"__symbolic":"select","expression":{"__symbolic":"reference","module":"@angular/forms","name":"Validators"},"member":"minLength"},"arguments":[8]}]}]}],"RESET_PASSWORD_FORM":[{"__symbolic":"new","expression":{"__symbolic":"reference","name":"BaseField"},"arguments":[{"key":"email","label":"Email","type":"text","validators":[{"__symbolic":"select","expression":{"__symbolic":"reference","module":"@angular/forms","name":"Validators"},"member":"required"},{"__symbolic":"call","expression":{"__symbolic":"select","expression":{"__symbolic":"reference","module":"@angular/forms","name":"Validators"},"member":"minLength"},"arguments":[8]}]}]}],"UPDATE_PASSWORD_FORM":[{"__symbolic":"new","expression":{"__symbolic":"reference","name":"BaseField"},"arguments":[{"key":"password","label":"Password","type":"password","validators":[{"__symbolic":"select","expression":{"__symbolic":"reference","module":"@angular/forms","name":"Validators"},"member":"required"},{"__symbolic":"call","expression":{"__symbolic":"select","expression":{"__symbolic":"reference","module":"@angular/forms","name":"Validators"},"member":"minLength"},"arguments":[8]}]}]},{"__symbolic":"new","expression":{"__symbolic":"reference","name":"BaseField"},"arguments":[{"key":"passwordConfirmation","label":"Password Confirmation","type":"password","validators":[{"__symbolic":"select","expression":{"__symbolic":"reference","module":"@angular/forms","name":"Validators"},"member":"required"},{"__symbolic":"call","expression":{"__symbolic":"select","expression":{"__symbolic":"reference","module":"@angular/forms","name":"Validators"},"member":"minLength"},"arguments":[8]}]}]},{"__symbolic":"new","expression":{"__symbolic":"reference","name":"BaseField"},"arguments":[{"key":"passwordCurrent","label":"Old Password","type":"password","validators":[{"__symbolic":"select","expression":{"__symbolic":"reference","module":"@angular/forms","name":"Validators"},"member":"required"},{"__symbolic":"call","expression":{"__symbolic":"select","expression":{"__symbolic":"reference","module":"@angular/forms","name":"Validators"},"member":"minLength"},"arguments":[8]}]}]}]}}]